.readthedocs.yaml
CHANGES.md
LICENSE
MANIFEST.in
README.md
setup.py
lasair/RL_consumer.py
lasair/__init__.py
lasair/__version__.py
lasair/lasair.py
lasair.egg-info/PKG-INFO
lasair.egg-info/SOURCES.txt
lasair.egg-info/dependency_links.txt
lasair.egg-info/requires.txt
lasair.egg-info/top_level.txt