Metadata-Version: 2.1
Name: lasair
Version: 0.1.1
Summary: A client for the Lasair database
Home-page: https://github.com/lasair-uk/lasair_api
Author: RoyDavidWilliams
Author-email: roydavidwilliams@gmail.com
License: MIT
Classifier: Development Status :: 4 - Beta
Classifier: License :: OSI Approved :: MIT License
Classifier: Programming Language :: Python :: 3.6
Classifier: Topic :: Utilities
Requires-Python: >=3.6
License-File: LICENSE
Requires-Dist: requests
